README.md
setup.py
ly_web_auto_base/__init__.py
ly_web_auto_base/base.py
ly_web_auto_base/driver.py
ly_web_auto_base.egg-info/PKG-INFO
ly_web_auto_base.egg-info/SOURCES.txt
ly_web_auto_base.egg-info/dependency_links.txt
ly_web_auto_base.egg-info/requires.txt
ly_web_auto_base.egg-info/top_level.txt