Metadata-Version: 2.1
Name: ly-web-auto-base
Version: 0.0.1
Summary: UI自动化基类
Home-page: UNKNOWN
Author: yjy
Author-email: 
License: UNKNOWN
Platform: UNKNOWN
Classifier: Programming Language :: Python :: 3
Classifier: License :: OSI Approved :: MIT License
Requires-Python: >=3.9
